MANIFEST.in
README.md
requirements.txt
setup.cfg
setup.py
versioneer.py
src/i3_xfce.egg-info/PKG-INFO
src/i3_xfce.egg-info/SOURCES.txt
src/i3_xfce.egg-info/dependency_links.txt
src/i3_xfce.egg-info/entry_points.txt
src/i3_xfce.egg-info/requires.txt
src/i3_xfce.egg-info/top_level.txt
src/i3xfce/__init__.py
src/i3xfce/__main__.py
src/i3xfce/_version.py
src/i3xfce/core.py
src/i3xfce/loggers.py
src/i3xfce/resources/roles/install/base/files/autostart/compton.desktop
src/i3xfce/resources/roles/install/base/files/autostart/i3.desktop
src/i3xfce/resources/roles/install/base/files/autostart/xfce4-panel.desktop
src/i3xfce/resources/roles/install/base/files/xfce/xfce4-session.xml.patch
src/i3xfce/resources/roles/install/base/tasks/main.yml
src/i3xfce/resources/roles/install/themes/files/compton/compton.conf
src/i3xfce/resources/roles/install/themes/files/conky/conkyrc_left
src/i3xfce/resources/roles/install/themes/files/conky/conkyrc_right
src/i3xfce/resources/roles/install/themes/files/fonts/openlogos.ttf
src/i3xfce/resources/roles/install/themes/files/i3/config
src/i3xfce/resources/roles/install/themes/files/lightdm/lightdm-gtk-greeter.conf
src/i3xfce/resources/roles/install/themes/files/xfce/Numix_Lightbulb.png
src/i3xfce/resources/roles/install/themes/files/xfce/xfce4-notifyd.xml
src/i3xfce/resources/roles/install/themes/files/xfce/xsettings.xml
src/i3xfce/resources/roles/install/themes/tasks/main.yml
src/i3xfce/resources/roles/install/utilities/files/.vimrc
src/i3xfce/resources/roles/install/utilities/files/albert.conf
src/i3xfce/resources/roles/install/utilities/files/zsh/zshrc
src/i3xfce/resources/roles/install/utilities/tasks/main.yml
src/i3xfce/resources/roles/uninstall/base/tasks/main.yml
src/i3xfce/resources/roles/uninstall/themes/tasks/main.yml
src/i3xfce/resources/roles/uninstall/utilities/tasks/main.yml