Metadata-Version: 1.0
Name: i3-xfce
Version: 0.6.3
Summary: I3 installer for xfce4
Home-page: http://github.com/aacebedo/i3-xfce
Author: Alexandre ACEBEDO
Author-email: Alexandre ACEBEDO
License: LGPLv3
Keywords: i3 xfce
Platform: UNKNOWN
